{
    "kind": "List",
    "apiVersion": "v1",
    "metadata": {},
    "items": [
        {
            "kind": "BuildConfig",
            "apiVersion": "v1",
            "metadata": {
                "name": "httpd-example",
                "creationTimestamp": null,
                "labels": {
                    "app": "httpd-example",
                    "template": "httpd-example"
                },
                "annotations": {
                    "description": "Defines how to build the application",
                    "template.alpha.openshift.io/wait-for-ready": "true"
                }
            },
            "spec": {
                "triggers": [
                    {
                        "type": "ImageChange",
                        "imageChange": {}
                    },
                    {
                        "type": "ConfigChange"
                    },
                    {
                        "type": "GitHub",
                        "github": {
                            "secret": "Mi0MYimGOJHyPscM6srtdViTAPxUG8CqJsFhbgxe"
                        }
                    },
                    {
                        "type": "Generic",
                        "generic": {
                            "secret": "hi6GvRQP5RFiCclkJAyAFrh0SV2iDRLrQABEmEDP"
                        }
                    }
                ],
                "runPolicy": "Serial",
                "source": {
                    "type": "Git",
                    "git": {
                        "uri": "https://github.com/openshift/httpd-ex.git"
                    }
                },
                "strategy": {
                    "type": "Source",
                    "sourceStrategy": {
                        "from": {
                            "kind": "ImageStreamTag",
                            "namespace": "openshift",
                            "name": "httpd:2.4"
                        }
                    }
                },
                "output": {
                    "to": {
                        "kind": "ImageStreamTag",
                        "name": "httpd-example:latest"
                    }
                },
                "resources": {},
                "postCommit": {},
                "nodeSelector": null
            },
            "status": {
                "lastVersion": 0
            }
        }
    ]
}
